dots/__init__.py
dots/__main__.py
dots/callbacks.py
dots/chars.py
dots/constants.py
dots/dot.py
dots/environment.py
dots/exceptions.py
dots/getchar.py
dots/interpreter.py
dots/states.py
dots/terminalsize.py
dots/vector.py
dots/world.py
dots/libs/bool_not.dots
dots/libs/clone.dots
dots/libs/compress.dots
dots/libs/decompress.dots
dots/libs/for_in_range.dots
dots/libs/list.dots
dots/libs/neg.dots
dots/libs/negate_id.dots
dots/libs/storage.dots
dots/libs/val_to_id.dots
dots/libs/wait.dots
asciidots-1.4.0.dist-info/METADATA
asciidots-1.4.0.dist-info/WHEEL
asciidots-1.4.0.dist-info/entry_points.txt
asciidots-1.4.0.dist-info/top_level.txt
asciidots-1.4.0.dist-info/RECORD
