Metadata-Version: 2.1
Name: asciidots
Version: 1.4.0
Summary: Interpreter for the AsciiDots esolang.
Home-page: https://github.com/aaronduino/asciidots
Author: Aaron Janse
Author-email: gitduino@gmail.com
License: APGL-v3.0
Keywords: asciidots esolang esoteric ascii dataflow language programming fun
Classifier: Development Status :: 5 - Production/Stable
Classifier: Intended Audience :: Education
Classifier: Intended Audience :: Other Audience
Classifier: Intended Audience :: Science/Research
Classifier: Topic :: Games/Entertainment
Classifier: Topic :: Other/Nonlisted Topic
Classifier: Topic :: Software Development :: Interpreters
Classifier: Operating System :: OS Independent
Classifier: License :: OSI Approved :: GNU Affero General Public License v3
Classifier: Programming Language :: Python :: 2
Classifier: Programming Language :: Python :: 2.6
Classifier: Programming Language :: Python :: 2.7
Classifier: Programming Language :: Python :: 3
Classifier: Programming Language :: Python :: 3.3
Classifier: Programming Language :: Python :: 3.4
Classifier: Programming Language :: Python :: 3.5
Classifier: Programming Language :: Python :: 3.6
Requires-Python: >=2.6, <4
Requires-Dist: Click
